cookiecutter_project_upgrader/__init__.py
cookiecutter_project_upgrader/_version.py
cookiecutter_project_upgrader/cli.py
cookiecutter_project_upgrader/logic.py
cookiecutter_project_upgrader/py.typed
cookiecutter_project_upgrader-1.3.1.dist-info/LICENSE
cookiecutter_project_upgrader-1.3.1.dist-info/METADATA
cookiecutter_project_upgrader-1.3.1.dist-info/WHEEL
cookiecutter_project_upgrader-1.3.1.dist-info/entry_points.txt
cookiecutter_project_upgrader-1.3.1.dist-info/top_level.txt
cookiecutter_project_upgrader-1.3.1.dist-info/RECORD
