Metadata-Version: 2.1
Name: cookiecutter-project-upgrader
Version: 1.3.1
Summary: upgrade projects created from a Cookiecutter template
Home-page: https://github.com/thomasjahoda/cookiecutter_project_upgrader
Author: Thomas Jahoda
Author-email: thomasjahoda@users.noreply.github.com
License: MIT license
Keywords: cookiecutter_project_upgrader
Platform: UNKNOWN
Classifier: Development Status :: 2 - Pre-Alpha
Classifier: Intended Audience :: Developers
Classifier: License :: OSI Approved :: MIT License
Classifier: Natural Language :: English
Classifier: Programming Language :: Python :: 3
Classifier: Programming Language :: Python :: 3.6
Classifier: Programming Language :: Python :: 3.7
Requires-Dist: cookiecutter
Requires-Dist: click (>=7.0)
Provides-Extra: dev
Requires-Dist: pytest-cookies (~=0.3.0) ; extra == 'dev'
Requires-Dist: pip (>=19.0.2) ; extra == 'dev'
Requires-Dist: bumpversion (>=0.5.3) ; extra == 'dev'
Requires-Dist: wheel (>=0.32.3) ; extra == 'dev'
Requires-Dist: watchdog (>=0.9.0) ; extra == 'dev'
Requires-Dist: flake8 (>=3.6.0) ; extra == 'dev'
Requires-Dist: tox (>=3.6.1) ; extra == 'dev'
Requires-Dist: coverage (>=4.5.2) ; extra == 'dev'
Requires-Dist: Sphinx (>=1.8.3) ; extra == 'dev'
Requires-Dist: twine (>=1.12.1) ; extra == 'dev'
Requires-Dist: pluggy (>=0.7.0) ; extra == 'dev'
Requires-Dist: mypy (>=0.782) ; extra == 'dev'
Requires-Dist: pytest (>=3.8.2) ; extra == 'dev'
Requires-Dist: pytest-runner (>=4.2) ; extra == 'dev'
Requires-Dist: pytest-mock (>=1.10.1) ; extra == 'dev'
Requires-Dist: pytest-cov (>=2.7.1) ; extra == 'dev'
